facer/__init__.py
facer/draw.py
facer/io.py
facer/show.py
facer/transform.py
facer/util.py
facer/version.py
facer/face_alignment/__init__.py
facer/face_alignment/base.py
facer/face_alignment/farl.py
facer/face_alignment/network/__init__.py
facer/face_alignment/network/common.py
facer/face_alignment/network/geometry.py
facer/face_alignment/network/mmseg.py
facer/face_alignment/network/transformers.py
facer/face_attribute/__init__.py
facer/face_attribute/base.py
facer/face_attribute/farl.py
facer/face_detection/__init__.py
facer/face_detection/base.py
facer/face_detection/retinaface.py
facer/face_parsing/__init__.py
facer/face_parsing/base.py
facer/face_parsing/farl.py
facer/farl/__init__.py
facer/farl/classification.py
facer/farl/model.py
pyfacer-0.0.5.dist-info/LICENSE
pyfacer-0.0.5.dist-info/METADATA
pyfacer-0.0.5.dist-info/WHEEL
pyfacer-0.0.5.dist-info/top_level.txt
pyfacer-0.0.5.dist-info/RECORD
