Metadata-Version: 2.1
Name: pyfacer
Version: 0.0.5
Summary: Face related toolkit
Home-page: https://github.com/FacePerceiver/facer
Author: FacePerceiver
License: MIT
Project-URL: Documentation, https://github.com/FacePerceiver/facer
Project-URL: Source, https://github.com/FacePerceiver/facer
Project-URL: Tracker, https://github.com/FacePerceiver/facer/issues
Keywords: face-detection pytorch RetinaFace face-parsing farl face-alignment
License-File: LICENSE
Requires-Dist: torch >=1.9.1
Requires-Dist: torchvision
Requires-Dist: timm
Requires-Dist: pillow
Requires-Dist: numpy
Requires-Dist: ipywidgets
Requires-Dist: scikit-image
Requires-Dist: matplotlib
Requires-Dist: validators
Requires-Dist: requests
Requires-Dist: opencv-python
